hypr/__init__.py
hypr/app.py
hypr/config.py
hypr/converters.py
hypr/globals.py
hypr/request.py
hypr/router.py
hypr/testing.py
hypr/web_exceptions.py
hypr/helpers/__init__.py
hypr/helpers/mini_dsl.py
hypr/models/__init__.py
hypr/models/base.py
hypr/models/exc.py
hypr/models/sqlite.py
hypr/providers/__init__.py
hypr/providers/base.py
hypr/providers/crud.py
hypr/providers/security.py
hypr/serializers/__init__.py
hypr/serializers/accept.py
hypr/serializers/json_serializer.py
hypr-0.8.2.dist-info/DESCRIPTION.rst
hypr-0.8.2.dist-info/METADATA
hypr-0.8.2.dist-info/RECORD
hypr-0.8.2.dist-info/WHEEL
hypr-0.8.2.dist-info/metadata.json
hypr-0.8.2.dist-info/top_level.txt
