Metadata-Version: 2.0
Name: hypr
Version: 0.8.2
Summary: Build a secure and RESTful hypermedia API.
Home-page: https://project-hypr.github.io
Author: Morgan Delahaye-Prat
Author-email: mdp@sillog.net
License: BSD
Platform: any
Classifier: Development Status :: 4 - Beta
Classifier: Programming Language :: Python
Classifier: Programming Language :: Python :: 3
Classifier: Programming Language :: Python :: 3.4
Classifier: Programming Language :: Python :: 3.5
Requires-Dist: aiohttp (==1.2.0)
Requires-Dist: tasklocals (==0.2)
